artyui/__init__.py
artyui/artyui.py
artyui-1.2.dist-info/METADATA
artyui-1.2.dist-info/WHEEL
artyui-1.2.dist-info/top_level.txt
artyui-1.2.dist-info/RECORD
