Metadata-Version: 2.1
Name: artyui
Version: 1.2
Summary: Многофункциональная библиотека, которая имеет в себе кучу полезных вещей, такие как: Логарифмы, Очень большой выбор тригонометрических функций, константы, и так далее...
Author: artemycreater
Requires-Dist: numpy
